e2b_charts/__init__.py
e2b_charts/charts/__init__.py
e2b_charts/charts/bars.py
e2b_charts/charts/base.py
e2b_charts/charts/pie.py
e2b_charts/charts/planar.py
e2b_charts/main.py
e2b_charts/utils/__init__.py
e2b_charts/utils/filtering.py
e2b_charts/utils/rounding.py
e2b_charts-0.0.4.dist-info/LICENSE
e2b_charts-0.0.4.dist-info/METADATA
e2b_charts-0.0.4.dist-info/WHEEL
e2b_charts-0.0.4.dist-info/RECORD
